smartlib/__init__.py
smartlib/compiler.py
smartlib/contract.py
smartlib/network.py
smartlib/utils.py
smartlib/wallet.py
smartlib-0.1.0.dist-info/licenses/LICENSE
smartlib-0.1.0.dist-info/METADATA
smartlib-0.1.0.dist-info/WHEEL
smartlib-0.1.0.dist-info/top_level.txt
smartlib-0.1.0.dist-info/RECORD
